setup.py
hupu_package/__init__.py
hupu_package/aliyun.py
hupu_package.egg-info/PKG-INFO
hupu_package.egg-info/SOURCES.txt
hupu_package.egg-info/dependency_links.txt
hupu_package.egg-info/top_level.txt