Metadata-Version: 1.0
Name: hupu-package
Version: 1.1
Summary: Upload file to oss
Home-page: https://www.hupu.com
Author: daizhanglong
Author-email: daizhanglong@hupu.com
License: MIT
Platform: UNKNOWN
